gempy_legacy/__init__.py
gempy_legacy/gempy_api.py
gempy_legacy/addons/__init__.py
gempy_legacy/addons/gempy_to_rexfile.py
gempy_legacy/addons/map2gempy.py
gempy_legacy/addons/rex_api.py
gempy_legacy/api_modules/__init__.py
gempy_legacy/api_modules/aux_func.py
gempy_legacy/api_modules/editing.py
gempy_legacy/api_modules/getters.py
gempy_legacy/api_modules/io.py
gempy_legacy/api_modules/setters.py
gempy_legacy/assets/__init__.py
gempy_legacy/assets/coKriging.py
gempy_legacy/assets/decision_making.py
gempy_legacy/assets/geophysics.py
gempy_legacy/assets/kriging.py
gempy_legacy/assets/spill_analysis.py
gempy_legacy/assets/topology.py
gempy_legacy/bayesian/__init__.py
gempy_legacy/bayesian/aesara_op.py
gempy_legacy/bayesian/axes_utils.py
gempy_legacy/bayesian/fields.py
gempy_legacy/bayesian/joyplot.py
gempy_legacy/bayesian/plot_posterior.py
gempy_legacy/bayesian/posterior_analysis_DEP.py
gempy_legacy/bayesian/posterior_analysis_elisa.py
gempy_legacy/core/__init__.py
gempy_legacy/core/checkers.py
gempy_legacy/core/colors.py
gempy_legacy/core/data.py
gempy_legacy/core/grid.py
gempy_legacy/core/interpolator.py
gempy_legacy/core/meta_data.py
gempy_legacy/core/model.py
gempy_legacy/core/qgrid_integration.py
gempy_legacy/core/solution.py
gempy_legacy/core/structure.py
gempy_legacy/core/surfaces.py
gempy_legacy/core/xsolution.py
gempy_legacy/core/aesara_modules/__init__.py
gempy_legacy/core/aesara_modules/aesara_export.py
gempy_legacy/core/aesara_modules/aesara_graph.py
gempy_legacy/core/aesara_modules/aesara_graph_pro.py
gempy_legacy/core/aesara_modules/aesara_kriging.py
gempy_legacy/core/data_modules/__init__.py
gempy_legacy/core/data_modules/geometric_data.py
gempy_legacy/core/data_modules/orientations.py
gempy_legacy/core/data_modules/scaling_system.py
gempy_legacy/core/data_modules/stack.py
gempy_legacy/core/data_modules/surface_points.py
gempy_legacy/core/grid_modules/__init__.py
gempy_legacy/core/grid_modules/create_topography.py
gempy_legacy-2.3.2.dist-info/LICENSE
gempy_legacy-2.3.2.dist-info/METADATA
gempy_legacy-2.3.2.dist-info/WHEEL
gempy_legacy-2.3.2.dist-info/top_level.txt
gempy_legacy-2.3.2.dist-info/RECORD
