Metadata-Version: 2.1
Name: gempy_legacy
Version: 2.3.2
Summary: An Open-source, Python-based 3-D structural geological modeling software.
Home-page: https://github.com/cgre-aachen/gempy
Author: Miguel de la Varga, Alexander Zimmerman, Elisa Heim, Alexander Schaaf, Fabian Stamm, Florian Wellmann, Jan Niederau, Andrew Annex, Alexander Juestel
Author-email: miguel@terranigma-solutions.com
License: LGPL v3
Keywords: geology,3-D modeling,structural geology,uncertainty
License-File: LICENSE
Requires-Dist: pandas ==2.0.1
Requires-Dist: aesara
Requires-Dist: pymc
Requires-Dist: matplotlib
Requires-Dist: numpy
Requires-Dist: pytest
Requires-Dist: seaborn >=0.9
Requires-Dist: networkx
Requires-Dist: scikit-image >=0.17
Requires-Dist: scikit-learn
Requires-Dist: pyvista ==0.39.1
Requires-Dist: pyvistaqt ==0.10.0
Requires-Dist: pyqt5
Requires-Dist: iPython
Requires-Dist: xarray
